README.md
setup.cfg
setup.py
lib/lieu/__init__.py
lib/lieu/address.py
lib/lieu/api.py
lib/lieu/coordinates.py
lib/lieu/dedupe.py
lib/lieu/encoding.py
lib/lieu/floats.py
lib/lieu/information_gain.py
lib/lieu/input.py
lib/lieu/similarity.py
lib/lieu/tfidf.py
lib/lieu/word_index.py
lib/lieu.egg-info/PKG-INFO
lib/lieu.egg-info/SOURCES.txt
lib/lieu.egg-info/dependency_links.txt
lib/lieu.egg-info/not-zip-safe
lib/lieu.egg-info/requires.txt
lib/lieu.egg-info/top_level.txt
lib/lieu/spark/__init__.py
lib/lieu/spark/dedupe.py
lib/lieu/spark/geo_word_index.py
lib/lieu/spark/information_gain.py
lib/lieu/spark/tfidf.py
lib/lieu/spark/utils.py
scripts/dedupe_geojson